tiktok/__init__.py
tiktok/business/__init__.py
tiktok/business/client.py
tiktok/business/oauth2.py
tiktok/business/services/__init__.py
tiktok/business/services/ad.py
tiktok/business/services/ad_group.py
tiktok/business/services/advertiser.py
tiktok/business/services/audience.py
tiktok/business/services/campaign.py
tiktok/business/services/constants.py
tiktok/business/services/creative.py
tiktok/business/services/identity.py
tiktok/business/services/reports.py
TikTok_Business_API-1.8.dist-info/LICENSE
TikTok_Business_API-1.8.dist-info/METADATA
TikTok_Business_API-1.8.dist-info/WHEEL
TikTok_Business_API-1.8.dist-info/top_level.txt
TikTok_Business_API-1.8.dist-info/RECORD
