Metadata-Version: 2.1
Name: TikTok-Business-API
Version: 1.8
Summary: Minimal api wrapper for the TikTok Business API
Home-page: https://github.com/Sharashchandra/TikTok-Business-API
Author: Sharashchandra Desai
Author-email: Sharashchandra Desai <sharashchandra.desai@gmail.com>
License: MIT License
Project-URL: Homepage, https://github.com/Sharashchandra/TikTok-Business-API
Project-URL: Bug Tracker, https://github.com/Sharashchandra/TikTok-Business-API/issues
Keywords: tiktok,business,api,wrapper
Classifier: Development Status :: 4 - Beta
Classifier: Environment :: Console
Classifier: Intended Audience :: Developers
Classifier: Operating System :: OS Independent
Classifier: Programming Language :: Python
Requires-Python: >=3.11
License-File: LICENSE
Requires-Dist: requests
